{
    "general": {
        "key": "WY36XGDK",
        "rid1": "dr",
        "rid2": "null",
        "study_notes": "null",
        "model_notes": {
          "model_1": "4 years horizon; full sample includes 1870–2006 but excluding World War 1 period, from 1914 to 1919 and also excluding World War 2, from 1939 to 1947.",
          "model_2": "4 years horizon; only post World War 2 sample, from 1948 to 2006.",
          "model_3": "10 year horizon instead of 4 years horizon; full sample includes 1870–2006 but excluding World War 1 period, from 1914 to 1919 and also excluding World War 2, from 1939 to 1947.",
          "model_4": "10 year horizon instead of 4 years horizon; only post World War 2 sample, from 1948 to 2006.",
          "model_5": "estimates from Table D1 in Appendix; economy is in a boom; full sample includes 1870–2006 but excluding World War 1 period, from 1914 to 1919 and also excluding World War 2, from 1939 to 1947.",
          "model_6": "estimates from Table D1 in Appendix; economy is in a slump; full sample includes 1870–2006 but excluding World War 1 period, from 1914 to 1919 and also excluding World War 2, from 1939 to 1947.",
          "model_7": "estimates from Table D1 in Appendix; economy is in a boom; only post World War 2 sample, from 1948 to 2006.",
          "model_8": "estimates from Table D1 in Appendix; economy is in a slump; only post World War 2 sample, from 1948 to 2006.",
          "model_9": "estimates from Table D2 in Appendix; economy is in a high inflation regime; full sample includes 1870–2006 but excluding World War 1 period, from 1914 to 1919 and also excluding World War 2, from 1939 to 1947.",
          "model_10": "estimates from Table D2 in Appendix; economy is in a low inflation regime; full sample includes 1870–2006 but excluding World War 1 period, from 1914 to 1919 and also excluding World War 2, from 1939 to 1947",
          "model_11": "estimates from Table D2 in Appendix; economy is in a high inflation regime; only post World War 2 sample, from 1948 to 2006.",
          "model_12": "estimates from Table D2 in Appendix; economy is in a low inflation regime; only post World War 2 sample, from 1948 to 2006.",
          "model_13": "estimates from Table D3 in Appendix; economy is in a high mortage credit growth regime; full sample includes 1870–2006 but excluding World War 1 period, from 1914 to 1919 and also excluding World War 2, from 1939 to 1947.",
          "model_14": "estimates from Table D3 in Appendix; economy is in a low mortage credit growth regime; full sample includes 1870–2006 but excluding World War 1 period, from 1914 to 1919 and also excluding World War 2, from 1939 to 1947.",
          "model_15": "estimates from Table D3 in Appendix; economy is in a high mortage credit growth regime; only post World War 2 sample, from 1948 to 2006.",
          "model_16": "estimates from Table D3 in Appendix; economy is in a low mortage credit growth regime; only post World War 2 sample, from 1948 to 2006.",
          "model_17": "estimates from Table D4 in Appendix; economy is in a high non-mortage credit growth regime; full sample includes 1870–2006 but excluding World War 1 period, from 1914 to 1919 and also excluding World War 2, from 1939 to 1947.",
          "model_18": "estimates from Table D4 in Appendix; economy is in a low non-mortage credit growth regime; full sample includes 1870–2006 but excluding World War 1 period, from 1914 to 1919 and also excluding World War 2, from 1939 to 1947.",
          "model_19": "estimates from Table D4 in Appendix; economy is in a high non-mortage credit growth regime; only post World War 2 sample, from 1948 to 2006.",
          "model_20": "estimates from Table D4 in Appendix; economy is in a low non-mortage credit growth regime; only post World War 2 sample, from 1948 to 2006."
        },
        "figure": {
          "model_1": 2,
          "model_2": "Appendix C.1",
          "model_3": "Appendix C.3",
          "model_4": "Appendix C.4",
          "model_5": "null",
          "model_6": "null",
          "model_7": "null",
          "model_8": "null",
          "model_9": "null",
          "model_10": "null",
          "model_11": "null",
          "model_12": "null",
          "model_13": "null",
          "model_14": "null",
          "model_15": "null",
          "model_16": "null",
          "model_17": "null",
          "model_18": "null",
          "model_19": "null",
          "model_20": "null"
        },
        "page": {
          "model_1": 35,
          "model_2": "Appendix 8",
          "model_3": "Appendix 10",
          "model_4": "Appendix 11",
          "model_5": "Appendix 13",
          "model_6": "Appendix 13",
          "model_7": "Appendix 13",
          "model_8": "Appendix 13",
          "model_9": "Appendix 13",
          "model_10": "Appendix 13",
          "model_11": "Appendix 13",
          "model_12": "Appendix 13",
          "model_13": "Appendix 13",
          "model_14": "Appendix 13",
          "model_15": "Appendix 13",
          "model_16": "Appendix 13",
          "model_17": "Appendix 14",
          "model_18": "Appendix 14",
          "model_19": "Appendix 14",
          "model_20": "Appendix 14"
        },
        "irf": {
          "model_1": true,
          "model_2": true,
          "model_3": true,
          "model_4": true,
          "model_5": false,
          "model_6": false,
          "model_7": false,
          "model_8": false,
          "model_9": false,
          "model_10": false,
          "model_11": false,
          "model_12": false,
          "model_13": false,
          "model_14": false,
          "model_15": false,
          "model_16": false,
          "model_17": false,
          "model_18": false,
          "model_19": false,
          "model_20": false
        },
        "cum": true
    },
    "impulse_and_response_variables": {
        "inttype": "lev_a_short_term_rate",
        "size": "100bp",
        "axis_trans": false,
        "dep": {
          "model_1": "logdiff_a_rgdp logdiff_a_cpi",
          "model_2": "logdiff_a_rgdp logdiff_a_cpi",
          "model_3": "logdiff_a_rgdp logdiff_a_cpi",
          "model_4": "logdiff_a_rgdp logdiff_a_cpi",
          "model_5": "log_a_rgdp log_a_cpi",
          "model_6": "log_a_rgdp log_a_cpi",
          "model_7": "log_a_rgdp log_a_cpi",
          "model_8": "log_a_rgdp log_a_cpi",
          "model_9": "log_a_rgdp log_a_cpi",
          "model_10": "log_a_rgdp log_a_cpi",
          "model_11": "log_a_rgdp log_a_cpi",
          "model_12": "log_a_rgdp log_a_cpi",
          "model_13": "log_a_rgdp log_a_cpi",
          "model_14": "log_a_rgdp log_a_cpi",
          "model_15": "log_a_rgdp log_a_cpi",
          "model_16": "log_a_rgdp log_a_cpi",
          "model_17": "log_a_rgdp log_a_cpi",
          "model_18": "log_a_rgdp log_a_cpi",
          "model_19": "log_a_rgdp log_a_cpi",
          "model_20": "log_a_rgdp log_a_cpi"
        },
        "conf": "90 & 1_SE",
        "main": "other",
        "prefer": {
          "model_1": true,
          "model_2": true,
          "model_3": true,
          "model_4": true,
          "model_5": false,
          "model_6": false,
          "model_7": false,
          "model_8": false,
          "model_9": false,
          "model_10": false,
          "model_11": false,
          "model_12": false,
          "model_13": false,
          "model_14": false,
          "model_15": false,
          "model_16": false,
          "model_17": false,
          "model_18": false,
          "model_19": false,
          "model_20": false
        }
    },
    "identification_strategy": {
        "iv": true,
        "forecast_based": false,
        "nr": false,
        "event": false,
        "chol": false,
        "svar": false,
        "signr": false,
        "hf": false,
        "heteroskedas": false,
        "longrun": false,
        "idother": false
    },
    "estimation_method": {
        "var": false,
        "lp": true,
        "vecm": false,
        "dyn_ols": "false",
        "fvar": false,
        "tvar": false,
        "gvar": false,
        "bayes": false,
        "dsge": false,
        "varother": false
    },
    "regime_dependence": {
        "lor": {
          "model_1": false,
          "model_2": false,
          "model_3": false,
          "model_4": false,
          "model_5": false,
          "model_6": true,
          "model_7": false,
          "model_8": true,
          "model_9": false,
          "model_10": false,
          "model_11": false,
          "model_12": false,
          "model_13": false,
          "model_14": false,
          "model_15": false,
          "model_16": false,
          "model_17": false,
          "model_18": false,
          "model_19": false,
          "model_20": false
        },
        "upr": {
          "model_1": false,
          "model_2": false,
          "model_3": false,
          "model_4": false,
          "model_5": true,
          "model_6": false,
          "model_7": true,
          "model_8": false,
          "model_9": false,
          "model_10": false,
          "model_11": false,
          "model_12": false,
          "model_13": false,
          "model_14": false,
          "model_15": false,
          "model_16": false,
          "model_17": false,
          "model_18": false,
          "model_19": false,
          "model_20": false
        },
        "scr": false,
        "dcr": false,
        "hike": false,
        "cut": false
    },
    "data_frequency": {
        "annual": true,
        "quarter": false,
        "month": false
    },
    "country_composition": {
        "list_of_countries": "AU BE CA DK FI FR DE IT JP NL NO PT ES SE CH GB US",
        "n_of_countries": 17
    },
    "further_data_characteristics": {
        "panel": true,
        "start": {
          "model_1": "1870",
          "model_2": "1948",
          "model_3": "1870",
          "model_4": "1948",
          "model_5": "1870",
          "model_6": "1870",
          "model_7": "1948",
          "model_8": "1948",
          "model_9": "1870",
          "model_10": "1870",
          "model_11": "1948",
          "model_12": "1948",
          "model_13": "1870",
          "model_14": "1870",
          "model_15": "1948",
          "model_16": "1948",
          "model_17": "1870",
          "model_18": "1870",
          "model_19": "1948",
          "model_20": "1948"
        },
        "end": "2006",
        "samplesize": {
          "model_1": "null",
          "model_2": "null",
          "model_3": "null",
          "model_4": "null",
          "model_5": 424,
          "model_6": 424,
          "model_7": 424,
          "model_8": 424,
          "model_9": 583,
          "model_10": 294,
          "model_11": 583,
          "model_12": 294,
          "model_13": 349,
          "model_14": 506,
          "model_15": 349,
          "model_16": 506,
          "model_17": 405,
          "model_18": 450,
          "model_19": 405,
          "model_20": 450
        }
    },
    "control_variables": {
        "comprice": false,
        "outpgap": false,
        "find": true,
        "eglob": true,
        "cbind": false,
        "fexch": true,
        "inflexp": false,
        "foreignir": false,
        "fx": false,
        "lrir": true
    },
    "econometric_details": {
        "pure_rate_shock": true,
        "convent": true,
        "decomposition": false
    },
    "publication_characteristics": {
        "cbanker": true
    }
}

